vest/__init__.py
vest/cli.py
vest/data/__init__.py
vest/data/config.json
vest-0.0.15.dist-info/METADATA
vest-0.0.15.dist-info/WHEEL
vest-0.0.15.dist-info/entry_points.txt
vest-0.0.15.dist-info/top_level.txt
vest-0.0.15.dist-info/RECORD
