Metadata-Version: 2.1
Name: vest
Version: 0.0.15
Summary: UNKNOWN
Home-page: https://github.com/mattf1n/vest
Author: mattf1n
License: UNKNOWN
Platform: UNKNOWN
Requires-Dist: Click
Requires-Dist: tabulate
Requires-Dist: pprint
Requires-Dist: robin-stocks
Requires-Dist: gnuplotlib
Requires-Dist: numpy
Requires-Dist: halo
